bda.plone.checkout-2.0b1-py3.9-nspkg.pth
bda/plone/checkout/__init__.py
bda/plone/checkout/configure.zcml
bda/plone/checkout/i18n.sh
bda/plone/checkout/interfaces.py
bda/plone/checkout/permissions.py
bda/plone/checkout/permissions.zcml
bda/plone/checkout/profiles.zcml
bda/plone/checkout/setuphandlers.py
bda/plone/checkout/vocabularies.py
bda/plone/checkout/browser/__init__.py
bda/plone/checkout/browser/cart_overview.pt
bda/plone/checkout/browser/checkout.css
bda/plone/checkout/browser/checkout.css.map
bda/plone/checkout/browser/checkout.js
bda/plone/checkout/browser/checkout.min.css
bda/plone/checkout/browser/configure.zcml
bda/plone/checkout/browser/form.py
bda/plone/checkout/browser/view.pt
bda/plone/checkout/browser/forms/accept_terms.yaml
bda/plone/checkout/browser/forms/billing_address.yaml
bda/plone/checkout/browser/forms/delivery_address.yaml
bda/plone/checkout/browser/forms/order_comment.yaml
bda/plone/checkout/browser/forms/payment_selection.yaml
bda/plone/checkout/browser/forms/personal_data.yaml
bda/plone/checkout/browser/forms/shipping_selection.yaml
bda/plone/checkout/locales/bda.plone.checkout.pot
bda/plone/checkout/locales/manual.pot
bda/plone/checkout/locales/de/LC_MESSAGES/bda.plone.checkout.po
bda/plone/checkout/locales/en/LC_MESSAGES/bda.plone.checkout.po
bda/plone/checkout/locales/fr/LC_MESSAGES/bda.plone.checkout.po
bda/plone/checkout/locales/it/LC_MESSAGES/bda.plone.checkout.po
bda/plone/checkout/locales/nl/LC_MESSAGES/bda.plone.checkout.po
bda/plone/checkout/locales/nn/LC_MESSAGES/bda.plone.checkout.po
bda/plone/checkout/locales/no/LC_MESSAGES/bda.plone.checkout.po
bda/plone/checkout/profiles/default/browserlayer.xml
bda/plone/checkout/profiles/default/metadata.xml
bda/plone/checkout/profiles/default/registry.xml
bda/plone/checkout/profiles/default/rolemap.xml
bda/plone/checkout/profiles/uninstall/browserlayer.xml
bda/plone/checkout/profiles/uninstall/registry.xml
bda/plone/checkout/tests/__init__.py
bda/plone/checkout/tests/test_checkout.py
bda.plone.checkout-2.0b1.dist-info/LICENSE.rst
bda.plone.checkout-2.0b1.dist-info/LICENSE_GPL.rst
bda.plone.checkout-2.0b1.dist-info/METADATA
bda.plone.checkout-2.0b1.dist-info/WHEEL
bda.plone.checkout-2.0b1.dist-info/namespace_packages.txt
bda.plone.checkout-2.0b1.dist-info/top_level.txt
bda.plone.checkout-2.0b1.dist-info/RECORD
